zrb_noto/__init__.py
zrb_noto/__main__.py
zrb_noto/_config.py
zrb_noto/_env.py
zrb_noto/_group.py
zrb_noto/_helper.py
zrb_noto/_input.py
zrb_noto/lint.py
zrb_noto/lint.sh
zrb_noto/list.py
zrb_noto/log/__init__.py
zrb_noto/log/_group.py
zrb_noto/log/_helper.py
zrb_noto/log/_input.py
zrb_noto/log/add.py
zrb_noto/log/edit.py
zrb_noto/log/list.py
zrb_noto/note.py
zrb_noto/sync.py
zrb_noto/sync.sh
zrb_noto/todo/__init__.py
zrb_noto/todo/_group.py
zrb_noto/todo/_helper.py
zrb_noto/todo/_input.py
zrb_noto/todo/_item.py
zrb_noto/todo/add.py
zrb_noto/todo/archive.py
zrb_noto/todo/complete.py
zrb_noto/todo/delete.py
zrb_noto/todo/edit.py
zrb_noto/todo/find.py
zrb_noto/todo/kanban/__init__.py
zrb_noto/todo/kanban/_helper.py
zrb_noto/todo/kanban/kanban.py
zrb_noto/todo/list.py
zrb_noto/todo/start.py
zrb_noto/todo/stop.py
zrb_noto/todo/update.py
zrb_noto/wiki.py
zrb_noto-0.0.9.dist-info/METADATA
zrb_noto-0.0.9.dist-info/WHEEL
zrb_noto-0.0.9.dist-info/entry_points.txt
zrb_noto-0.0.9.dist-info/RECORD
