Metadata-Version: 2.1
Name: zrb-noto
Version: 0.0.9
Summary: Personal todo and logging management
Home-page: https://github.com/state-alchemists/noto
License: AGPL-3.0-or-later
Author: Go Frendi Gunawan
Author-email: gofrendiasgard@gmail.com
Requires-Python: >=3.10.0,<4.0.0
Classifier: License :: OSI Approved :: GNU Affero General Public License v3 or later (AGPLv3+)
Classifier: Programming Language :: Python :: 3
Classifier: Programming Language :: Python :: 3.10
Classifier: Programming Language :: Python :: 3.11
Classifier: Programming Language :: Python :: 3.12
Requires-Dist: zrb (>=0.23.0)
Project-URL: Documentation, https://github.com/state-alchemists/noto
Project-URL: Repository, https://github.com/state-alchemists/noto
